LICENSE.txt
MANIFEST.in
README.rst
requirements.core.txt
requirements.txt
setup.py
core_visualization_insitu_app/__init__.py
core_visualization_insitu_app/admin.py
core_visualization_insitu_app/apps.py
core_visualization_insitu_app/discover.py
core_visualization_insitu_app/menus.py
core_visualization_insitu_app/models.py
core_visualization_insitu_app/settings.py
core_visualization_insitu_app/tasks.py
core_visualization_insitu_app/urls.py
core_visualization_insitu_app.egg-info/PKG-INFO
core_visualization_insitu_app.egg-info/SOURCES.txt
core_visualization_insitu_app.egg-info/dependency_links.txt
core_visualization_insitu_app.egg-info/requires.txt
core_visualization_insitu_app.egg-info/top_level.txt
core_visualization_insitu_app/components/__init__.py
core_visualization_insitu_app/components/insitu_data/__init__.py
core_visualization_insitu_app/components/insitu_data/api.py
core_visualization_insitu_app/components/insitu_data/models.py
core_visualization_insitu_app/components/insitu_data/operations.py
core_visualization_insitu_app/permissions/__init__.py
core_visualization_insitu_app/permissions/discover.py
core_visualization_insitu_app/permissions/rights.py
core_visualization_insitu_app/static/core_visualization_insitu_app/admin/css/cache.css
core_visualization_insitu_app/static/core_visualization_insitu_app/admin/js/build_visualization_data.js
core_visualization_insitu_app/static/core_visualization_insitu_app/admin/js/build_visualization_data_raw.js
core_visualization_insitu_app/static/core_visualization_insitu_app/common/css/loading_background.css
core_visualization_insitu_app/static/core_visualization_insitu_app/user/css/frame.css
core_visualization_insitu_app/static/core_visualization_insitu_app/user/css/main.css
core_visualization_insitu_app/static/core_visualization_insitu_app/user/img/no_data_400x300.jpg
core_visualization_insitu_app/static/core_visualization_insitu_app/user/img/no_data_layer.jpg
core_visualization_insitu_app/static/core_visualization_insitu_app/user/js/access_layer_number.js
core_visualization_insitu_app/static/core_visualization_insitu_app/user/js/access_layer_number_raw.js
core_visualization_insitu_app/static/core_visualization_insitu_app/user/js/display_blobs.js
