Metadata-Version: 2.1
Name: core-visualization-insitu-app
Version: 1.3.1
Summary: Visualization Insitu app
Home-page: https://github.com/usnistgov/core_visualization_insitu_app
Author: NIST IT Lab
Author-email: itl_inquiries@nist.gov
License: UNKNOWN
Platform: UNKNOWN
License-File: LICENSE.txt
